aitk/__init__.py
aitk/_version.py
aitk/algorithms/__init__.py
aitk/algorithms/ga.py
aitk/algorithms/novelty.py
aitk/algorithms/neat/__init__.py
aitk/algorithms/neat/activations.py
aitk/algorithms/neat/aggregations.py
aitk/algorithms/neat/attributes.py
aitk/algorithms/neat/checkpoint.py
aitk/algorithms/neat/config.py
aitk/algorithms/neat/distributed.py
aitk/algorithms/neat/genes.py
aitk/algorithms/neat/genome.py
aitk/algorithms/neat/graphs.py
aitk/algorithms/neat/math_util.py
aitk/algorithms/neat/parallel.py
aitk/algorithms/neat/population.py
aitk/algorithms/neat/reporting.py
aitk/algorithms/neat/reproduction.py
aitk/algorithms/neat/species.py
aitk/algorithms/neat/stagnation.py
aitk/algorithms/neat/statistics.py
aitk/algorithms/neat/threaded.py
aitk/algorithms/neat/visualize.py
aitk/algorithms/neat/ctrnn/__init__.py
aitk/algorithms/neat/iznn/__init__.py
aitk/algorithms/neat/nn/__init__.py
aitk/algorithms/neat/nn/feed_forward.py
aitk/algorithms/neat/nn/recurrent.py
aitk/networks/__init__.py
aitk/networks/callbacks.py
aitk/networks/network.py
aitk/networks/utils.py
aitk/networks/watchers.py
aitk/robots/__init__.py
aitk/robots/cart.py
aitk/robots/config.py
aitk/robots/dashboard.py
aitk/robots/hit.py
aitk/robots/robot.py
aitk/robots/utils.py
aitk/robots/watchers.py
aitk/robots/world.py
aitk/robots/backends/__init__.py
aitk/robots/backends/base.py
aitk/robots/backends/canvas.py
aitk/robots/backends/debug.py
aitk/robots/backends/pil.py
aitk/robots/backends/svg.py
aitk/robots/datasets/__init__.py
aitk/robots/datasets/coil100.py
aitk/robots/datasets/coil20.py
aitk/robots/datasets/utils.py
aitk/robots/devices/__init__.py
aitk/robots/devices/base.py
aitk/robots/devices/beacon.py
aitk/robots/devices/bulbs.py
aitk/robots/devices/cameras.py
aitk/robots/devices/compass.py
aitk/robots/devices/lightsensors.py
aitk/robots/devices/rangesensors.py
aitk/robots/devices/smellsensors.py
aitk/robots/worlds/duck-scribbler-no-walls.json
aitk/robots/worlds/soccer-640x401.png
aitk-3.1.0.dist-info/METADATA
aitk-3.1.0.dist-info/WHEEL
aitk-3.1.0.dist-info/top_level.txt
aitk-3.1.0.dist-info/RECORD
