Metadata-Version: 2.4
Name: aitk
Version: 3.1.0
Summary: Python tools for AI
Home-page: https://github.com/ArtificialIntelligenceToolkit/aitk
Author: Douglas Blank
License: BSD-3-Clause
Keywords: ai,artificial intelligence,robots,simulator,jupyter,python,machine learning,neural networks,keras,tensorflow
Platform: Linux
Platform: Mac OS X
Platform: Windows
Classifier: License :: OSI Approved :: BSD License
Classifier: Programming Language :: Python
Classifier: Programming Language :: Python :: 3
Classifier: Programming Language :: Python :: 3.9
Classifier: Programming Language :: Python :: 3.10
Classifier: Programming Language :: Python :: 3.11
Classifier: Framework :: Jupyter
Requires-Python: >=3.9
Requires-Dist: Pillow
Requires-Dist: ipywidgets
Requires-Dist: tqdm
Requires-Dist: numpy
Requires-Dist: matplotlib
Requires-Dist: tensorflow>=2.17.0
Dynamic: author
Dynamic: classifier
Dynamic: description
Dynamic: description-content-type
Dynamic: home-page
Dynamic: keywords
Dynamic: license
Dynamic: platform
Dynamic: requires-dist
Dynamic: requires-python
Dynamic: summary
